Metadata-Version: 1.0
Name: ricotta
Version: 0.0.5
Summary: Visualize bird songs
Home-page: https://github.com/mrcslws/ricotta
Author: Marcus Lewis
Author-email: mrcslws@gmail.com
License: UNKNOWN
Platform: UNKNOWN
